/*    */ package br.com.arremate.d;
/*    */ 
/*    */ import br.com.arremate.g.b;
/*    */ import br.com.arremate.g.e;
/*    */ import br.com.arremate.l.h;
/*    */ import br.com.arremate.l.q.b.e;
/*    */ import java.text.DecimalFormat;
/*    */ import java.util.List;
/*    */ import java.util.StringJoiner;
/*    */ import org.slf4j.Logger;
/*    */ import org.slf4j.LoggerFactory;
/*    */ 
/*    */ 
/*    */ 
/*    */ 
/*    */ 
/*    */ 
/*    */ 
/*    */ 
/*    */ 
/*    */ 
/*    */ 
/*    */ 
/*    */ 
/*    */ 
/*    */ public class a
/*    */ {
/* 28 */   private static final Logger a = LoggerFactory.getLogger(a.class);
/*    */   
/*    */   private final f a;
/*    */   
/*    */   private final boolean g;
/*    */   private double a;
/*    */   private int E;
/*    */   private boolean h;
/*    */   
/*    */   public a(f paramf, boolean paramBoolean) {
/* 38 */     this.a = paramf;
/* 39 */     this.g = paramBoolean;
/* 40 */     this.E = 0;
/* 41 */     this.h = false;
/*    */   }
/*    */   
/*    */   public h a() throws b, e, br.com.arremate.g.a {
/*    */     // Byte code:
/*    */     //   0: aload_0
/*    */     //   1: getfield a : Lbr/com/arremate/d/f;
/*    */     //   4: invokevirtual a : ()Lbr/com/arremate/l/q/b/e;
/*    */     //   7: astore_2
/*    */     //   8: aload_0
/*    */     //   9: aload_2
/*    */     //   10: invokespecial a : (Lbr/com/arremate/l/q/b/e;)Ljava/util/List;
/*    */     //   13: astore_3
/*    */     //   14: aload_2
/*    */     //   15: invokevirtual bv : ()Z
/*    */     //   18: ifeq -> 30
/*    */     //   21: aload_0
/*    */     //   22: aload_3
/*    */     //   23: invokespecial a : (Ljava/util/List;)Lbr/com/arremate/l/h;
/*    */     //   26: astore_1
/*    */     //   27: goto -> 72
/*    */     //   30: aload_0
/*    */     //   31: getfield E : I
/*    */     //   34: ifle -> 47
/*    */     //   37: aload_0
/*    */     //   38: getfield E : I
/*    */     //   41: iconst_3
/*    */     //   42: if_icmpgt -> 47
/*    */     //   45: aconst_null
/*    */     //   46: areturn
/*    */     //   47: aload_2
/*    */     //   48: invokevirtual a : ()Lbr/com/arremate/f/s;
/*    */     //   51: getstatic br/com/arremate/f/s.a : Lbr/com/arremate/f/s;
/*    */     //   54: if_acmpne -> 66
/*    */     //   57: aload_0
/*    */     //   58: aload_3
/*    */     //   59: invokespecial b : (Ljava/util/List;)Lbr/com/arremate/l/h;
/*    */     //   62: astore_1
/*    */     //   63: goto -> 72
/*    */     //   66: aload_0
/*    */     //   67: aload_3
/*    */     //   68: invokespecial c : (Ljava/util/List;)Lbr/com/arremate/l/h;
/*    */     //   71: astore_1
/*    */     //   72: aload_1
/*    */     //   73: ifnull -> 184
/*    */     //   76: aload_0
/*    */     //   77: getfield a : D
/*    */     //   80: dconst_0
/*    */     //   81: dcmpl
/*    */     //   82: ifle -> 141
/*    */     //   85: aload_1
/*    */     //   86: invokevirtual m : ()D
/*    */     //   89: invokestatic valueOf : (D)Ljava/math/BigDecimal;
/*    */     //   92: aload_0
/*    */     //   93: getfield a : D
/*    */     //   96: invokestatic valueOf : (D)Ljava/math/BigDecimal;
/*    */     //   99: invokevirtual compareTo : (Ljava/math/BigDecimal;)I
/*    */     //   102: iflt -> 141
/*    */     //   105: aload_2
/*    */     //   106: invokevirtual bv : ()Z
/*    */     //   109: ifne -> 141
/*    */     //   112: aload_2
/*    */     //   113: invokevirtual ay : ()Z
/*    */     //   116: ifeq -> 141
/*    */     //   119: aload_1
/*    */     //   120: aload_0
/*    */     //   121: getfield a : D
/*    */     //   124: ldc2_w 0.01
/*    */     //   127: dsub
/*    */     //   128: invokevirtual q : (D)V
/*    */     //   131: getstatic br/com/arremate/d/a.a : Lorg/slf4j/Logger;
/*    */     //   134: ldc 'ultimo lance calculado igual a lance calculado atual, decrementando 1 centavo'
/*    */     //   136: invokeinterface info : (Ljava/lang/String;)V
/*    */     //   141: aload_0
/*    */     //   142: getfield a : Lbr/com/arremate/d/f;
/*    */     //   145: aload_1
/*    */     //   146: invokevirtual m : ()D
/*    */     //   149: invokevirtual b : (D)Z
/*    */     //   152: ifne -> 176
/*    */     //   155: new br/com/arremate/l/h
/*    */     //   158: dup
/*    */     //   159: aload_2
/*    */     //   160: invokevirtual l : ()D
/*    */     //   163: invokespecial <init> : (D)V
/*    */     //   166: astore_1
/*    */     //   167: aload_0
/*    */     //   168: getfield a : Lbr/com/arremate/d/f;
/*    */     //   171: ldc 'Lance Derradeiro'
/*    */     //   173: invokevirtual i : (Ljava/lang/String;)V
/*    */     //   176: aload_0
/*    */     //   177: aload_1
/*    */     //   178: invokevirtual m : ()D
/*    */     //   181: putfield a : D
/*    */     //   184: aload_1
/*    */     //   185: areturn
/*    */     // Line number table:
/*    */     //   Java source line number -> byte code offset
/*    */     //   #46	-> 0
/*    */     //   #47	-> 8
/*    */     //   #49	-> 14
/*    */     //   #50	-> 21
/*    */     //   #52	-> 30
/*    */     //   #53	-> 45
/*    */     //   #56	-> 47
/*    */     //   #57	-> 57
/*    */     //   #59	-> 66
/*    */     //   #63	-> 72
/*    */     //   #64	-> 76
/*    */     //   #65	-> 106
/*    */     //   #66	-> 119
/*    */     //   #67	-> 131
/*    */     //   #71	-> 141
/*    */     //   #72	-> 155
/*    */     //   #73	-> 167
/*    */     //   #76	-> 176
/*    */     //   #78	-> 184
/*    */   }
/*    */   
/*    */   private List<h> a(e parame) {
/*    */     // Byte code:
/*    */     //   0: aconst_null
/*    */     //   1: astore_2
/*    */     //   2: aload_0
/*    */     //   3: getfield g : Z
/*    */     //   6: ifeq -> 146
/*    */     //   9: aload_0
/*    */     //   10: getfield E : I
/*    */     //   13: ifne -> 146
/*    */     //   16: aload_0
/*    */     //   17: getfield a : Lbr/com/arremate/d/f;
/*    */     //   20: invokevirtual e : ()Ljava/util/List;
/*    */     //   23: astore_2
/*    */     //   24: aload_0
/*    */     //   25: aload_2
/*    */     //   26: invokeinterface size : ()I
/*    */     //   31: putfield E : I
/*    */     //   34: aload_0
/*    */     //   35: getfield a : Lbr/com/arremate/d/f;
/*    */     //   38: invokevirtual b : ()Lbr/com/arremate/d/g;
/*    */     //   41: ifnull -> 111
/*    */     //   44: aload_0
/*    */     //   45: getfield E : I
/*    */     //   48: iconst_1
/*    */     //   49: if_icmple -> 111
/*    */     //   52: aload_0
/*    */     //   53: getfield E : I
/*    */     //   56: iconst_3
/*    */     //   57: if_icmpgt -> 111
/*    */     //   60: aload_0
/*    */     //   61: getfield a : Lbr/com/arremate/d/f;
/*    */     //   64: invokevirtual b : ()Lbr/com/arremate/d/g;
/*    */     //   67: ldc ''
/*    */     //   69: iconst_5
/*    */     //   70: anewarray java/lang/CharSequence
/*    */     //   73: dup
/*    */     //   74: iconst_0
/*    */     //   75: ldc 'O Item '
/*    */     //   77: aastore
/*    */     //   78: dup
/*    */     //   79: iconst_1
/*    */     //   80: aload_1
/*    */     //   81: invokevirtual bo : ()Ljava/lang/String;
/*    */     //   84: aastore
/*    */     //   85: dup
/*    */     //   86: iconst_2
/*    */     //   87: ldc ' possui '
/*    */     //   89: aastore
/*    */     //   90: dup
/*    */     //   91: iconst_3
/*    */     //   92: aload_0
/*    */     //   93: getfield E : I
/*    */     //   96: invokestatic toString : (I)Ljava/lang/String;
/*    */     //   99: aastore
/*    */     //   100: dup
/*    */     //   101: iconst_4
/*    */     //   102: ldc ' fornecedore(s). Será enviado lance somente na etapa fechada.'
/*    */     //   104: aastore
/*    */     //   105: invokestatic join : (Ljava/lang/CharSequence;[Ljava/lang/CharSequence;)Ljava/lang/String;
/*    */     //   108: invokevirtual l : (Ljava/lang/String;)V
/*    */     //   111: goto -> 146
/*    */     //   114: astore_3
/*    */     //   115: aload_0
/*    */     //   116: getfield a : Lbr/com/arremate/d/f;
/*    */     //   119: invokevirtual b : ()Lbr/com/arremate/d/g;
/*    */     //   122: ldc ' - '
/*    */     //   124: iconst_2
/*    */     //   125: anewarray java/lang/CharSequence
/*    */     //   128: dup
/*    */     //   129: iconst_0
/*    */     //   130: aload_1
/*    */     //   131: invokevirtual bo : ()Ljava/lang/String;
/*    */     //   134: aastore
/*    */     //   135: dup
/*    */     //   136: iconst_1
/*    */     //   137: ldc 'Falha ao capturar o número de panticipantes do item'
/*    */     //   139: aastore
/*    */     //   140: invokestatic join : (Ljava/lang/CharSequence;[Ljava/lang/CharSequence;)Ljava/lang/String;
/*    */     //   143: invokevirtual l : (Ljava/lang/String;)V
/*    */     //   146: aload_2
/*    */     //   147: areturn
/*    */     // Line number table:
/*    */     //   Java source line number -> byte code offset
/*    */     //   #82	-> 0
/*    */     //   #84	-> 2
/*    */     //   #86	-> 16
/*    */     //   #87	-> 24
/*    */     //   #90	-> 34
/*    */     //   #91	-> 60
/*    */     //   #94	-> 81
/*    */     //   #96	-> 96
/*    */     //   #92	-> 105
/*    */     //   #91	-> 108
/*    */     //   #103	-> 111
/*    */     //   #101	-> 114
/*    */     //   #102	-> 115
/*    */     //   #106	-> 146
/*    */     // Exception table:
/*    */     //   from	to	target	type
/*    */     //   16	111	114	br/com/arremate/g/d
/*    */   }
/*    */   
/*    */   private h a(List<h> paramList) {
/*    */     // Byte code:
/*    */     //   0: aload_0
/*    */     //   1: getfield a : Lbr/com/arremate/d/f;
/*    */     //   4: invokevirtual a : ()Lbr/com/arremate/l/q/b/e;
/*    */     //   7: astore_2
/*    */     //   8: aload_2
/*    */     //   9: invokevirtual n : ()Ljava/math/BigDecimal;
/*    */     //   12: astore_3
/*    */     //   13: aload_2
/*    */     //   14: invokevirtual w : ()I
/*    */     //   17: getstatic br/com/arremate/f/v.a : Lbr/com/arremate/f/v;
/*    */     //   20: invokevirtual v : ()I
/*    */     //   23: if_icmpne -> 48
/*    */     //   26: aload_3
/*    */     //   27: aload_2
/*    */     //   28: invokevirtual f : ()D
/*    */     //   31: invokestatic valueOf : (D)Ljava/math/BigDecimal;
/*    */     //   34: invokevirtual compareTo : (Ljava/math/BigDecimal;)I
/*    */     //   37: iflt -> 44
/*    */     //   40: iconst_1
/*    */     //   41: goto -> 67
/*    */     //   44: iconst_0
/*    */     //   45: goto -> 67
/*    */     //   48: aload_3
/*    */     //   49: aload_2
/*    */     //   50: invokevirtual f : ()D
/*    */     //   53: invokestatic valueOf : (D)Ljava/math/BigDecimal;
/*    */     //   56: invokevirtual compareTo : (Ljava/math/BigDecimal;)I
/*    */     //   59: ifgt -> 66
/*    */     //   62: iconst_1
/*    */     //   63: goto -> 67
/*    */     //   66: iconst_0
/*    */     //   67: istore #4
/*    */     //   69: iload #4
/*    */     //   71: ifne -> 121
/*    */     //   74: aload_3
/*    */     //   75: getstatic java/math/BigDecimal.ZERO : Ljava/math/BigDecimal;
/*    */     //   78: invokevirtual compareTo : (Ljava/math/BigDecimal;)I
/*    */     //   81: ifle -> 121
/*    */     //   84: aload_2
/*    */     //   85: invokevirtual z : ()J
/*    */     //   88: aload_2
/*    */     //   89: invokevirtual b : ()Lbr/com/arremate/l/b;
/*    */     //   92: invokevirtual w : ()J
/*    */     //   95: lcmp
/*    */     //   96: ifgt -> 121
/*    */     //   99: aload_2
/*    */     //   100: invokevirtual aR : ()Z
/*    */     //   103: ifeq -> 121
/*    */     //   106: aload_2
/*    */     //   107: invokevirtual aS : ()Z
/*    */     //   110: ifne -> 121
/*    */     //   113: aload_0
/*    */     //   114: getfield E : I
/*    */     //   117: iconst_1
/*    */     //   118: if_icmpne -> 123
/*    */     //   121: aconst_null
/*    */     //   122: areturn
/*    */     //   123: aload_0
/*    */     //   124: getfield E : I
/*    */     //   127: iconst_1
/*    */     //   128: if_icmple -> 419
/*    */     //   131: aload_0
/*    */     //   132: getfield E : I
/*    */     //   135: iconst_3
/*    */     //   136: if_icmpgt -> 419
/*    */     //   139: aload_1
/*    */     //   140: ifnonnull -> 151
/*    */     //   143: aload_0
/*    */     //   144: getfield a : Lbr/com/arremate/d/f;
/*    */     //   147: invokevirtual e : ()Ljava/util/List;
/*    */     //   150: astore_1
/*    */     //   151: iconst_0
/*    */     //   152: istore #5
/*    */     //   154: iload #5
/*    */     //   156: aload_1
/*    */     //   157: invokeinterface size : ()I
/*    */     //   162: if_icmpge -> 402
/*    */     //   165: aload_1
/*    */     //   166: iload #5
/*    */     //   168: invokeinterface get : (I)Ljava/lang/Object;
/*    */     //   173: checkcast br/com/arremate/l/h
/*    */     //   176: invokevirtual bb : ()Z
/*    */     //   179: ifeq -> 396
/*    */     //   182: iload #5
/*    */     //   184: aload_1
/*    */     //   185: invokeinterface size : ()I
/*    */     //   190: iconst_1
/*    */     //   191: isub
/*    */     //   192: if_icmpne -> 396
/*    */     //   195: aload_1
/*    */     //   196: iload #5
/*    */     //   198: iconst_1
/*    */     //   199: isub
/*    */     //   200: invokeinterface get : (I)Ljava/lang/Object;
/*    */     //   205: checkcast br/com/arremate/l/h
/*    */     //   208: astore #6
/*    */     //   210: aload_2
/*    */     //   211: invokevirtual w : ()I
/*    */     //   214: getstatic br/com/arremate/f/v.b : Lbr/com/arremate/f/v;
/*    */     //   217: invokevirtual v : ()I
/*    */     //   220: if_icmpne -> 248
/*    */     //   223: aload_3
/*    */     //   224: aload #6
/*    */     //   226: invokevirtual m : ()D
/*    */     //   229: invokestatic valueOf : (D)Ljava/math/BigDecimal;
/*    */     //   232: invokevirtual compareTo : (Ljava/math/BigDecimal;)I
/*    */     //   235: ifge -> 242
/*    */     //   238: iconst_1
/*    */     //   239: goto -> 243
/*    */     //   242: iconst_0
/*    */     //   243: istore #7
/*    */     //   245: goto -> 270
/*    */     //   248: aload_3
/*    */     //   249: aload #6
/*    */     //   251: invokevirtual m : ()D
/*    */     //   254: invokestatic valueOf : (D)Ljava/math/BigDecimal;
/*    */     //   257: invokevirtual compareTo : (Ljava/math/BigDecimal;)I
/*    */     //   260: ifle -> 267
/*    */     //   263: iconst_1
/*    */     //   264: goto -> 268
/*    */     //   267: iconst_0
/*    */     //   268: istore #7
/*    */     //   270: iload #7
/*    */     //   272: ifeq -> 396
/*    */     //   275: ldc '###,###,##0.0000'
/*    */     //   277: invokestatic a : (Ljava/lang/String;)Ljava/text/DecimalFormat;
/*    */     //   280: astore #8
/*    */     //   282: new java/util/StringJoiner
/*    */     //   285: dup
/*    */     //   286: ldc '; '
/*    */     //   288: invokespecial <init> : (Ljava/lang/CharSequence;)V
/*    */     //   291: astore #9
/*    */     //   293: aload_1
/*    */     //   294: aload #9
/*    */     //   296: aload #8
/*    */     //   298: <illegal opcode> accept : (Ljava/util/StringJoiner;Ljava/text/DecimalFormat;)Ljava/util/function/Consumer;
/*    */     //   303: invokeinterface forEach : (Ljava/util/function/Consumer;)V
/*    */     //   308: aload_0
/*    */     //   309: getfield a : Lbr/com/arremate/d/f;
/*    */     //   312: invokevirtual b : ()Lbr/com/arremate/d/g;
/*    */     //   315: ifnull -> 389
/*    */     //   318: ldc ''
/*    */     //   320: bipush #7
/*    */     //   322: anewarray java/lang/CharSequence
/*    */     //   325: dup
/*    */     //   326: iconst_0
/*    */     //   327: ldc 'Lance fechado'
/*    */     //   329: aastore
/*    */     //   330: dup
/*    */     //   331: iconst_1
/*    */     //   332: ldc ' ('
/*    */     //   334: aastore
/*    */     //   335: dup
/*    */     //   336: iconst_2
/*    */     //   337: aload #8
/*    */     //   339: aload_3
/*    */     //   340: invokevirtual format : (Ljava/lang/Object;)Ljava/lang/String;
/*    */     //   343: aastore
/*    */     //   344: dup
/*    */     //   345: iconst_3
/*    */     //   346: ldc ') '
/*    */     //   348: aastore
/*    */     //   349: dup
/*    */     //   350: iconst_4
/*    */     //   351: ldc 'não enviado por não possibilitar uma melhor colocação'
/*    */     //   353: aastore
/*    */     //   354: dup
/*    */     //   355: iconst_5
/*    */     //   356: ldc ' | '
/*    */     //   358: aastore
/*    */     //   359: dup
/*    */     //   360: bipush #6
/*    */     //   362: aload #9
/*    */     //   364: invokevirtual toString : ()Ljava/lang/String;
/*    */     //   367: aastore
/*    */     //   368: invokestatic join : (Ljava/lang/CharSequence;[Ljava/lang/CharSequence;)Ljava/lang/String;
/*    */     //   371: astore #10
/*    */     //   373: aload_0
/*    */     //   374: getfield a : Lbr/com/arremate/d/f;
/*    */     //   377: invokevirtual b : ()Lbr/com/arremate/d/g;
/*    */     //   380: aload #10
/*    */     //   382: aload_2
/*    */     //   383: invokevirtual bo : ()Ljava/lang/String;
/*    */     //   386: invokevirtual a : (Ljava/lang/String;Ljava/lang/String;)V
/*    */     //   389: aload_2
/*    */     //   390: iconst_1
/*    */     //   391: invokevirtual w : (Z)V
/*    */     //   394: aconst_null
/*    */     //   395: areturn
/*    */     //   396: iinc #5, 1
/*    */     //   399: goto -> 154
/*    */     //   402: goto -> 419
/*    */     //   405: astore #5
/*    */     //   407: getstatic br/com/arremate/d/a.a : Lorg/slf4j/Logger;
/*    */     //   410: ldc 'Erro ao capturar os melhores lances no lance fechado'
/*    */     //   412: aload #5
/*    */     //   414: invokeinterface warn : (Ljava/lang/String;Ljava/lang/Throwable;)V
/*    */     //   419: new br/com/arremate/l/h
/*    */     //   422: dup
/*    */     //   423: aload_3
/*    */     //   424: invokevirtual doubleValue : ()D
/*    */     //   427: invokespecial <init> : (D)V
/*    */     //   430: astore #5
/*    */     //   432: aload_0
/*    */     //   433: getfield a : Lbr/com/arremate/d/f;
/*    */     //   436: ldc 'Lance Fechado'
/*    */     //   438: invokevirtual i : (Ljava/lang/String;)V
/*    */     //   441: aload #5
/*    */     //   443: areturn
/*    */     // Line number table:
/*    */     //   Java source line number -> byte code offset
/*    */     //   #110	-> 0
/*    */     //   #111	-> 8
/*    */     //   #113	-> 13
/*    */     //   #114	-> 28
/*    */     //   #115	-> 50
/*    */     //   #117	-> 69
/*    */     //   #118	-> 78
/*    */     //   #119	-> 85
/*    */     //   #120	-> 100
/*    */     //   #121	-> 107
/*    */     //   #123	-> 121
/*    */     //   #126	-> 123
/*    */     //   #128	-> 139
/*    */     //   #129	-> 143
/*    */     //   #132	-> 151
/*    */     //   #133	-> 165
/*    */     //   #134	-> 195
/*    */     //   #137	-> 210
/*    */     //   #138	-> 223
/*    */     //   #140	-> 248
/*    */     //   #142	-> 270
/*    */     //   #143	-> 275
/*    */     //   #144	-> 282
/*    */     //   #146	-> 293
/*    */     //   #154	-> 308
/*    */     //   #155	-> 318
/*    */     //   #156	-> 373
/*    */     //   #159	-> 389
/*    */     //   #160	-> 394
/*    */     //   #132	-> 396
/*    */     //   #166	-> 402
/*    */     //   #164	-> 405
/*    */     //   #165	-> 407
/*    */     //   #169	-> 419
/*    */     //   #170	-> 432
/*    */     //   #171	-> 441
/*    */     // Exception table:
/*    */     //   from	to	target	type
/*    */     //   139	395	405	br/com/arremate/g/d
/*    */     //   396	402	405	br/com/arremate/g/d
/*    */   }
/*    */   
/*    */   private h b(List<h> paramList) throws br.com.arremate.g.a {
/*    */     // Byte code:
/*    */     //   0: aload_0
/*    */     //   1: getfield a : Lbr/com/arremate/d/f;
/*    */     //   4: invokevirtual a : ()Lbr/com/arremate/l/q/b/e;
/*    */     //   7: astore_2
/*    */     //   8: aload_2
/*    */     //   9: invokevirtual b : ()Lbr/com/arremate/l/b;
/*    */     //   12: astore_3
/*    */     //   13: aconst_null
/*    */     //   14: astore #4
/*    */     //   16: aload_1
/*    */     //   17: ifnonnull -> 28
/*    */     //   20: aload_0
/*    */     //   21: getfield a : Lbr/com/arremate/d/f;
/*    */     //   24: invokevirtual e : ()Ljava/util/List;
/*    */     //   27: astore_1
/*    */     //   28: aload_3
/*    */     //   29: invokevirtual aL : ()Z
/*    */     //   32: ifeq -> 49
/*    */     //   35: aload_0
/*    */     //   36: getfield a : Lbr/com/arremate/d/f;
/*    */     //   39: invokevirtual a : ()Lbr/com/arremate/k/b/a;
/*    */     //   42: aload_1
/*    */     //   43: aload_2
/*    */     //   44: invokevirtual c : (Ljava/util/List;Lbr/com/arremate/l/q/b/e;)Lbr/com/arremate/l/h;
/*    */     //   47: astore #4
/*    */     //   49: aload #4
/*    */     //   51: ifnonnull -> 64
/*    */     //   54: aload_0
/*    */     //   55: getfield a : Lbr/com/arremate/d/f;
/*    */     //   58: aload_1
/*    */     //   59: invokevirtual b : (Ljava/util/List;)Lbr/com/arremate/l/h;
/*    */     //   62: astore #4
/*    */     //   64: goto -> 80
/*    */     //   67: astore #5
/*    */     //   69: aload_0
/*    */     //   70: getfield a : Lbr/com/arremate/d/f;
/*    */     //   73: ldc 'enviar lance'
/*    */     //   75: aload #5
/*    */     //   77: invokevirtual a : (Ljava/lang/String;Lbr/com/arremate/g/d;)V
/*    */     //   80: aload #4
/*    */     //   82: areturn
/*    */     // Line number table:
/*    */     //   Java source line number -> byte code offset
/*    */     //   #175	-> 0
/*    */     //   #176	-> 8
/*    */     //   #177	-> 13
/*    */     //   #180	-> 16
/*    */     //   #181	-> 20
/*    */     //   #184	-> 28
/*    */     //   #185	-> 35
/*    */     //   #188	-> 49
/*    */     //   #189	-> 54
/*    */     //   #193	-> 64
/*    */     //   #191	-> 67
/*    */     //   #192	-> 69
/*    */     //   #195	-> 80
/*    */     // Exception table:
/*    */     //   from	to	target	type
/*    */     //   16	64	67	br/com/arremate/g/d
/*    */   }
/*    */   
/*    */   private h c(List<h> paramList) throws b, e {
/*    */     // Byte code:
/*    */     //   0: aload_0
/*    */     //   1: invokespecial o : ()Z
/*    */     //   4: ifne -> 15
/*    */     //   7: aload_0
/*    */     //   8: getfield a : Lbr/com/arremate/d/f;
/*    */     //   11: invokevirtual c : ()Lbr/com/arremate/l/h;
/*    */     //   14: areturn
/*    */     //   15: aconst_null
/*    */     //   16: astore_2
/*    */     //   17: aload_0
/*    */     //   18: getfield a : Lbr/com/arremate/d/f;
/*    */     //   21: invokevirtual a : ()Lbr/com/arremate/l/q/b/e;
/*    */     //   24: astore_3
/*    */     //   25: aload_1
/*    */     //   26: ifnonnull -> 37
/*    */     //   29: aload_0
/*    */     //   30: getfield a : Lbr/com/arremate/d/f;
/*    */     //   33: invokevirtual e : ()Ljava/util/List;
/*    */     //   36: astore_1
/*    */     //   37: aload_0
/*    */     //   38: iconst_0
/*    */     //   39: putfield h : Z
/*    */     //   42: aload_3
/*    */     //   43: invokevirtual b : ()Lbr/com/arremate/l/b;
/*    */     //   46: invokevirtual aL : ()Z
/*    */     //   49: ifeq -> 80
/*    */     //   52: aload_0
/*    */     //   53: getfield a : Lbr/com/arremate/d/f;
/*    */     //   56: invokevirtual a : ()Lbr/com/arremate/k/b/a;
/*    */     //   59: aload_1
/*    */     //   60: aload_3
/*    */     //   61: invokevirtual c : (Ljava/util/List;Lbr/com/arremate/l/q/b/e;)Lbr/com/arremate/l/h;
/*    */     //   64: astore_2
/*    */     //   65: aload_2
/*    */     //   66: ifnull -> 80
/*    */     //   69: aload_0
/*    */     //   70: getfield a : Lbr/com/arremate/d/f;
/*    */     //   73: ldc '1º Lugar'
/*    */     //   75: invokevirtual i : (Ljava/lang/String;)V
/*    */     //   78: aload_2
/*    */     //   79: areturn
/*    */     //   80: goto -> 223
/*    */     //   83: astore #4
/*    */     //   85: aload_0
/*    */     //   86: getfield a : Lbr/com/arremate/d/f;
/*    */     //   89: ldc 'enviar lance'
/*    */     //   91: aload #4
/*    */     //   93: invokevirtual a : (Ljava/lang/String;Lbr/com/arremate/g/d;)V
/*    */     //   96: aload_0
/*    */     //   97: getfield h : Z
/*    */     //   100: ifeq -> 194
/*    */     //   103: aload_3
/*    */     //   104: invokevirtual bu : ()Z
/*    */     //   107: ifeq -> 199
/*    */     //   110: aload_0
/*    */     //   111: getfield a : Lbr/com/arremate/d/f;
/*    */     //   114: aload_3
/*    */     //   115: invokevirtual f : ()D
/*    */     //   118: invokevirtual b : (D)Z
/*    */     //   121: ifeq -> 199
/*    */     //   124: new br/com/arremate/l/h
/*    */     //   127: dup
/*    */     //   128: aload_3
/*    */     //   129: invokevirtual l : ()D
/*    */     //   132: invokespecial <init> : (D)V
/*    */     //   135: astore_2
/*    */     //   136: aload_2
/*    */     //   137: new java/util/Date
/*    */     //   140: dup
/*    */     //   141: invokestatic a : ()Ljava/lang/Long;
/*    */     //   144: invokevirtual longValue : ()J
/*    */     //   147: getstatic java/util/concurrent/TimeUnit.MINUTES : Ljava/util/concurrent/TimeUnit;
/*    */     //   150: lconst_1
/*    */     //   151: invokevirtual toMillis : (J)J
/*    */     //   154: lsub
/*    */     //   155: invokespecial <init> : (J)V
/*    */     //   158: invokevirtual c : (Ljava/util/Date;)V
/*    */     //   161: aload_0
/*    */     //   162: getfield a : Lbr/com/arremate/d/f;
/*    */     //   165: ldc 'Lance Derradeiro'
/*    */     //   167: invokevirtual i : (Ljava/lang/String;)V
/*    */     //   170: aload_0
/*    */     //   171: getfield a : Lbr/com/arremate/d/f;
/*    */     //   174: invokevirtual b : ()Lbr/com/arremate/d/g;
/*    */     //   177: ldc 'Valor limite será enviado pois o portal está levando muito tempo para informar a lista de melhores lances'
/*    */     //   179: aload_3
/*    */     //   180: invokevirtual bo : ()Ljava/lang/String;
/*    */     //   183: invokevirtual a : (Ljava/lang/String;Ljava/lang/String;)V
/*    */     //   186: aload_0
/*    */     //   187: iconst_0
/*    */     //   188: putfield h : Z
/*    */     //   191: goto -> 199
/*    */     //   194: aload_0
/*    */     //   195: iconst_1
/*    */     //   196: putfield h : Z
/*    */     //   199: goto -> 223
/*    */     //   202: astore #4
/*    */     //   204: aload_0
/*    */     //   205: getfield a : Lbr/com/arremate/d/f;
/*    */     //   208: invokevirtual b : ()Lbr/com/arremate/d/g;
/*    */     //   211: aload #4
/*    */     //   213: invokevirtual getMessage : ()Ljava/lang/String;
/*    */     //   216: aload_3
/*    */     //   217: invokevirtual bo : ()Ljava/lang/String;
/*    */     //   220: invokevirtual a : (Ljava/lang/String;Ljava/lang/String;)V
/*    */     //   223: aload_1
/*    */     //   224: ifnull -> 242
/*    */     //   227: aload_1
/*    */     //   228: invokeinterface isEmpty : ()Z
/*    */     //   233: ifne -> 242
/*    */     //   236: aload_0
/*    */     //   237: aload_1
/*    */     //   238: invokespecial d : (Ljava/util/List;)Lbr/com/arremate/l/h;
/*    */     //   241: areturn
/*    */     //   242: aload_2
/*    */     //   243: areturn
/*    */     // Line number table:
/*    */     //   Java source line number -> byte code offset
/*    */     //   #199	-> 0
/*    */     //   #200	-> 7
/*    */     //   #203	-> 15
/*    */     //   #204	-> 17
/*    */     //   #207	-> 25
/*    */     //   #208	-> 29
/*    */     //   #211	-> 37
/*    */     //   #213	-> 42
/*    */     //   #214	-> 52
/*    */     //   #216	-> 65
/*    */     //   #217	-> 69
/*    */     //   #218	-> 78
/*    */     //   #243	-> 80
/*    */     //   #221	-> 83
/*    */     //   #222	-> 85
/*    */     //   #224	-> 96
/*    */     //   #225	-> 103
/*    */     //   #226	-> 124
/*    */     //   #228	-> 136
/*    */     //   #229	-> 161
/*    */     //   #231	-> 170
/*    */     //   #234	-> 180
/*    */     //   #232	-> 183
/*    */     //   #236	-> 186
/*    */     //   #239	-> 194
/*    */     //   #243	-> 199
/*    */     //   #241	-> 202
/*    */     //   #242	-> 204
/*    */     //   #245	-> 223
/*    */     //   #246	-> 236
/*    */     //   #249	-> 242
/*    */     // Exception table:
/*    */     //   from	to	target	type
/*    */     //   25	79	83	br/com/arremate/g/d
/*    */     //   25	79	202	br/com/arremate/g/a
/*    */   }
/*    */   
/*    */   private h d(List<h> paramList) throws b, e {
/*    */     // Byte code:
/*    */     //   0: aload_0
/*    */     //   1: aload_1
/*    */     //   2: invokespecial e : (Ljava/util/List;)Lbr/com/arremate/l/h;
/*    */     //   5: astore_2
/*    */     //   6: aload_2
/*    */     //   7: ifnonnull -> 33
/*    */     //   10: aload_0
/*    */     //   11: getfield a : Lbr/com/arremate/d/f;
/*    */     //   14: invokevirtual a : ()Lbr/com/arremate/l/q/b/e;
/*    */     //   17: invokevirtual b : ()Lbr/com/arremate/l/b;
/*    */     //   20: invokevirtual aJ : ()Z
/*    */     //   23: ifeq -> 33
/*    */     //   26: aload_0
/*    */     //   27: aload_1
/*    */     //   28: aload_2
/*    */     //   29: invokespecial a : (Ljava/util/List;Lbr/com/arremate/l/h;)Lbr/com/arremate/l/h;
/*    */     //   32: astore_2
/*    */     //   33: aload_2
/*    */     //   34: ifnull -> 39
/*    */     //   37: aload_2
/*    */     //   38: areturn
/*    */     //   39: aload_0
/*    */     //   40: getfield a : Lbr/com/arremate/d/f;
/*    */     //   43: aload_1
/*    */     //   44: invokevirtual c : (Ljava/util/List;)Lbr/com/arremate/l/h;
/*    */     //   47: areturn
/*    */     // Line number table:
/*    */     //   Java source line number -> byte code offset
/*    */     //   #253	-> 0
/*    */     //   #255	-> 6
/*    */     //   #256	-> 26
/*    */     //   #259	-> 33
/*    */     //   #260	-> 37
/*    */     //   #263	-> 39
/*    */   }
/*    */   
/*    */   private h e(List<h> paramList) throws e {
/*    */     // Byte code:
/*    */     //   0: aconst_null
/*    */     //   1: astore_2
/*    */     //   2: aload_0
/*    */     //   3: getfield a : Lbr/com/arremate/d/f;
/*    */     //   6: invokevirtual a : ()Lbr/com/arremate/l/q/b/e;
/*    */     //   9: astore_3
/*    */     //   10: aload_3
/*    */     //   11: invokevirtual b : ()Lbr/com/arremate/l/b;
/*    */     //   14: invokevirtual aK : ()Z
/*    */     //   17: ifeq -> 78
/*    */     //   20: aload_0
/*    */     //   21: getfield a : Lbr/com/arremate/d/f;
/*    */     //   24: invokevirtual a : ()Lbr/com/arremate/k/b/a;
/*    */     //   27: aload_1
/*    */     //   28: aload_3
/*    */     //   29: invokevirtual a : (Ljava/util/List;Lbr/com/arremate/l/q/b/e;)Lbr/com/arremate/l/h;
/*    */     //   32: astore_2
/*    */     //   33: aload_2
/*    */     //   34: ifnull -> 78
/*    */     //   37: aload_0
/*    */     //   38: getfield a : Lbr/com/arremate/d/f;
/*    */     //   41: aload_2
/*    */     //   42: invokevirtual j : ()I
/*    */     //   45: ifle -> 73
/*    */     //   48: new java/lang/StringBuilder
/*    */     //   51: dup
/*    */     //   52: invokespecial <init> : ()V
/*    */     //   55: aload_2
/*    */     //   56: invokevirtual j : ()I
/*    */     //   59: invokevirtual append : (I)Ljava/lang/StringBuilder;
/*    */     //   62: ldc 'º Lugar'
/*    */     //   64: invokevirtual append : (Ljava/lang/String;)Ljava/lang/StringBuilder;
/*    */     //   67: invokevirtual toString : ()Ljava/lang/String;
/*    */     //   70: goto -> 75
/*    */     //   73: ldc '10%'
/*    */     //   75: invokevirtual i : (Ljava/lang/String;)V
/*    */     //   78: aload_2
/*    */     //   79: areturn
/*    */     // Line number table:
/*    */     //   Java source line number -> byte code offset
/*    */     //   #267	-> 0
/*    */     //   #269	-> 2
/*    */     //   #270	-> 10
/*    */     //   #272	-> 20
/*    */     //   #274	-> 33
/*    */     //   #275	-> 37
/*    */     //   #279	-> 78
/*    */   }
/*    */   
/*    */   private h a(List<h> paramList, h paramh) throws b {
/*    */     // Byte code:
/*    */     //   0: aload_0
/*    */     //   1: getfield a : Lbr/com/arremate/d/f;
/*    */     //   4: invokevirtual a : ()Lbr/com/arremate/k/b/a;
/*    */     //   7: aload_1
/*    */     //   8: aload_0
/*    */     //   9: getfield a : Lbr/com/arremate/d/f;
/*    */     //   12: invokevirtual a : ()Lbr/com/arremate/l/q/b/e;
/*    */     //   15: invokevirtual b : (Ljava/util/List;Lbr/com/arremate/l/q/b/e;)Lbr/com/arremate/l/h;
/*    */     //   18: astore_3
/*    */     //   19: aload_3
/*    */     //   20: ifnull -> 54
/*    */     //   23: aload_3
/*    */     //   24: astore_2
/*    */     //   25: aload_0
/*    */     //   26: getfield a : Lbr/com/arremate/d/f;
/*    */     //   29: new java/lang/StringBuilder
/*    */     //   32: dup
/*    */     //   33: invokespecial <init> : ()V
/*    */     //   36: aload_2
/*    */     //   37: invokevirtual j : ()I
/*    */     //   40: invokevirtual append : (I)Ljava/lang/StringBuilder;
/*    */     //   43: ldc 'º Lugar'
/*    */     //   45: invokevirtual append : (Ljava/lang/String;)Ljava/lang/StringBuilder;
/*    */     //   48: invokevirtual toString : ()Ljava/lang/String;
/*    */     //   51: invokevirtual i : (Ljava/lang/String;)V
/*    */     //   54: goto -> 64
/*    */     //   57: astore_3
/*    */     //   58: aload_2
/*    */     //   59: ifnonnull -> 64
/*    */     //   62: aload_3
/*    */     //   63: athrow
/*    */     //   64: aload_2
/*    */     //   65: areturn
/*    */     // Line number table:
/*    */     //   Java source line number -> byte code offset
/*    */     //   #284	-> 0
/*    */     //   #286	-> 19
/*    */     //   #287	-> 23
/*    */     //   #288	-> 25
/*    */     //   #294	-> 54
/*    */     //   #290	-> 57
/*    */     //   #291	-> 58
/*    */     //   #292	-> 62
/*    */     //   #296	-> 64
/*    */     // Exception table:
/*    */     //   from	to	target	type
/*    */     //   0	54	57	br/com/arremate/g/b
/*    */   }
/*    */   
/*    */   private boolean o() {
/*    */     // Byte code:
/*    */     //   0: aload_0
/*    */     //   1: getfield a : Lbr/com/arremate/d/f;
/*    */     //   4: invokevirtual a : ()Lbr/com/arremate/l/q/b/e;
/*    */     //   7: invokevirtual b : ()Lbr/com/arremate/l/b;
/*    */     //   10: astore_1
/*    */     //   11: aload_1
/*    */     //   12: invokevirtual aK : ()Z
/*    */     //   15: ifne -> 32
/*    */     //   18: aload_1
/*    */     //   19: invokevirtual aJ : ()Z
/*    */     //   22: ifne -> 32
/*    */     //   25: aload_1
/*    */     //   26: invokevirtual aL : ()Z
/*    */     //   29: ifeq -> 36
/*    */     //   32: iconst_1
/*    */     //   33: goto -> 37
/*    */     //   36: iconst_0
/*    */     //   37: ireturn
/*    */     // Line number table:
/*    */     //   Java source line number -> byte code offset
/*    */     //   #300	-> 0
/*    */     //   #301	-> 11
/*    */   }
/*    */ }


/* Location:              C:\Arremate\Arremate.jar!\br\com\arremate\d\a.class
 * Java compiler version: 8 (52.0)
 * JD-Core Version:       1.1.3
 */