/*    */ package org.junit.a.e.a;
/*    */ 
/*    */ import java.util.List;
/*    */ import org.junit.a.e.e;
/*    */ import org.junit.a.e.g;
/*    */ 
/*    */ 
/*    */ 
/*    */ public class d
/*    */   extends e
/*    */ {
/*    */   private Class<?> k;
/*    */   
/*    */   public d(Class<?> paramClass) {
/* 15 */     this.k = paramClass;
/*    */   }
/*    */   
/*    */   public List<g> a(org.junit.a.e.d paramd) {
/*    */     // Byte code:
/*    */     //   0: aload_0
/*    */     //   1: getfield k : Ljava/lang/Class;
/*    */     //   4: invokevirtual getEnumConstants : ()[Ljava/lang/Object;
/*    */     //   7: astore_2
/*    */     //   8: new java/util/ArrayList
/*    */     //   11: dup
/*    */     //   12: invokespecial <init> : ()V
/*    */     //   15: astore_3
/*    */     //   16: aload_2
/*    */     //   17: astore #4
/*    */     //   19: aload #4
/*    */     //   21: arraylength
/*    */     //   22: istore #5
/*    */     //   24: iconst_0
/*    */     //   25: istore #6
/*    */     //   27: iload #6
/*    */     //   29: iload #5
/*    */     //   31: if_icmpge -> 64
/*    */     //   34: aload #4
/*    */     //   36: iload #6
/*    */     //   38: aaload
/*    */     //   39: astore #7
/*    */     //   41: aload_3
/*    */     //   42: aload #7
/*    */     //   44: invokevirtual toString : ()Ljava/lang/String;
/*    */     //   47: aload #7
/*    */     //   49: invokestatic a : (Ljava/lang/String;Ljava/lang/Object;)Lorg/junit/a/e/g;
/*    */     //   52: invokeinterface add : (Ljava/lang/Object;)Z
/*    */     //   57: pop
/*    */     //   58: iinc #6, 1
/*    */     //   61: goto -> 27
/*    */     //   64: aload_3
/*    */     //   65: areturn
/*    */     // Line number table:
/*    */     //   Java source line number -> byte code offset
/*    */     //   #20	-> 0
/*    */     //   #22	-> 8
/*    */     //   #23	-> 16
/*    */     //   #24	-> 41
/*    */     //   #23	-> 58
/*    */     //   #27	-> 64
/*    */   }
/*    */ }


/* Location:              C:\Arremate\Arremate.jar!\org\junit\a\e\a\d.class
 * Java compiler version: 5 (49.0)
 * JD-Core Version:       1.1.3
 */