/*     */ package com.google.a.d;
/*     */ 
/*     */ import com.google.a.a.a;
/*     */ import com.google.a.a.b;
/*     */ import com.google.a.b.D;
/*     */ import java.io.Serializable;
/*     */ import java.lang.reflect.Array;
/*     */ import java.util.Collection;
/*     */ import java.util.Iterator;
/*     */ import java.util.Map;
/*     */ import java.util.Set;
/*     */ import java.util.Spliterator;
/*     */ 
/*     */ 
/*     */ 
/*     */ 
/*     */ 
/*     */ 
/*     */ 
/*     */ 
/*     */ 
/*     */ 
/*     */ 
/*     */ 
/*     */ 
/*     */ 
/*     */ 
/*     */ 
/*     */ 
/*     */ 
/*     */ 
/*     */ 
/*     */ 
/*     */ 
/*     */ 
/*     */ 
/*     */ 
/*     */ 
/*     */ 
/*     */ 
/*     */ 
/*     */ 
/*     */ 
/*     */ 
/*     */ 
/*     */ 
/*     */ 
/*     */ 
/*     */ 
/*     */ 
/*     */ 
/*     */ 
/*     */ 
/*     */ 
/*     */ 
/*     */ 
/*     */ 
/*     */ 
/*     */ 
/*     */ 
/*     */ 
/*     */ 
/*     */ 
/*     */ 
/*     */ 
/*     */ 
/*     */ 
/*     */ 
/*     */ 
/*     */ 
/*     */ 
/*     */ 
/*     */ 
/*     */ 
/*     */ 
/*     */ 
/*     */ 
/*     */ @a
/*     */ @b(cl = true)
/*     */ public final class u<R, C, V>
/*     */   extends q<R, C, V>
/*     */   implements Serializable
/*     */ {
/*     */   private final bh<R> a;
/*     */   private final bh<C> b;
/*     */   private final bj<R, Integer> b;
/*     */   private final bj<C, Integer> c;
/*     */   private final V[][] a;
/*     */   private transient c a;
/*     */   private transient e a;
/*     */   private static final long serialVersionUID = 0L;
/*     */   
/*     */   public static <R, C, V> u<R, C, V> a(Iterable<? extends R> paramIterable, Iterable<? extends C> paramIterable1) {
/*  94 */     return new u<>(paramIterable, paramIterable1);
/*     */   }
/*     */ 
/*     */ 
/*     */ 
/*     */ 
/*     */ 
/*     */ 
/*     */ 
/*     */ 
/*     */ 
/*     */ 
/*     */ 
/*     */ 
/*     */ 
/*     */ 
/*     */ 
/*     */ 
/*     */ 
/*     */ 
/*     */ 
/*     */ 
/*     */ 
/*     */ 
/*     */ 
/*     */ 
/*     */   
/*     */   public static <R, C, V> u<R, C, V> a(cY<R, C, V> paramcY) {
/* 122 */     return (paramcY instanceof u) ? 
/* 123 */       new u<>((u<R, C, V>)paramcY) : 
/* 124 */       new u<>(paramcY);
/*     */   }
/*     */ 
/*     */ 
/*     */ 
/*     */ 
/*     */ 
/*     */ 
/*     */ 
/*     */ 
/*     */   
/*     */   private u(Iterable<? extends R> paramIterable, Iterable<? extends C> paramIterable1) {
/* 136 */     this.a = bh.b(paramIterable);
/* 137 */     this.b = bh.b(paramIterable1);
/* 138 */     D.checkArgument((this.a.isEmpty() == this.b.isEmpty()));
/*     */ 
/*     */ 
/*     */ 
/*     */ 
/*     */ 
/*     */ 
/*     */     
/* 146 */     this.b = bW.a((Collection<R>)this.a);
/* 147 */     this.c = bW.a((Collection)this.b);
/*     */ 
/*     */     
/* 150 */     Object[][] arrayOfObject = new Object[this.a.size()][this.b.size()];
/* 151 */     this.a = (e)arrayOfObject;
/*     */     
/* 153 */     eV();
/*     */   }
/*     */   
/*     */   private u(cY<R, C, V> paramcY) {
/* 157 */     this(paramcY.h(), paramcY.i());
/* 158 */     a(paramcY);
/*     */   }
/*     */   
/*     */   private u(u<R, C, V> paramu) {
/* 162 */     this.a = paramu.a;
/* 163 */     this.b = paramu.b;
/* 164 */     this.b = paramu.b;
/* 165 */     this.c = paramu.c;
/*     */     
/* 167 */     Object[][] arrayOfObject = new Object[this.a.size()][this.b.size()];
/* 168 */     this.a = (e)arrayOfObject;
/* 169 */     for (byte b = 0; b < this.a.size(); b++)
/* 170 */       System.arraycopy(paramu.a[b], 0, arrayOfObject[b], 0, (paramu.a[b]).length); 
/*     */   }
/*     */   
/*     */   private static abstract class a<K, V>
/*     */     extends bW.o<K, V> {
/*     */     private final bj<K, Integer> d;
/*     */     
/*     */     private a(bj<K, Integer> param1bj) {
/* 178 */       this.d = param1bj;
/*     */     }
/*     */ 
/*     */     
/*     */     public Set<K> keySet() {
/* 183 */       return this.d.j();
/*     */     }
/*     */     
/*     */     K getKey(int param1Int) {
/* 187 */       return this.d.j().c().get(param1Int);
/*     */     }
/*     */ 
/*     */ 
/*     */ 
/*     */ 
/*     */ 
/*     */ 
/*     */ 
/*     */     
/*     */     public int size() {
/* 198 */       return this.d.size();
/*     */     }
/*     */ 
/*     */     
/*     */     public boolean isEmpty() {
/* 203 */       return this.d.isEmpty();
/*     */     }
/*     */     
/*     */     Map.Entry<K, V> a(final int index) {
/* 207 */       D.b(index, size());
/* 208 */       return new g<K, V>(this)
/*     */         {
/*     */           public K getKey() {
/* 211 */             return (K)this.a.getKey(index);
/*     */           }
/*     */ 
/*     */           
/*     */           public V getValue() {
/* 216 */             return (V)this.a.getValue(index);
/*     */           }
/*     */ 
/*     */           
/*     */           public V setValue(V param2V) {
/* 221 */             return (V)this.a.setValue(index, param2V);
/*     */           }
/*     */         };
/*     */     }
/*     */ 
/*     */     
/*     */     Iterator<Map.Entry<K, V>> c() {
/* 228 */       return new b<Map.Entry<K, V>>(this, size())
/*     */         {
/*     */           protected Map.Entry<K, V> b(int param2Int) {
/* 231 */             return this.a.a(param2Int);
/*     */           }
/*     */         };
/*     */     }
/*     */ 
/*     */     
/*     */     Spliterator<Map.Entry<K, V>> b() {
/* 238 */       return D.a(size(), 16, this::a);
/*     */     }
/*     */ 
/*     */ 
/*     */ 
/*     */     
/*     */     public boolean containsKey(Object param1Object) {
/* 245 */       return this.d.containsKey(param1Object);
/*     */     }
/*     */ 
/*     */     
/*     */     public V get(Object param1Object) {
/* 250 */       Integer integer = this.d.get(param1Object);
/* 251 */       if (integer == null) {
/* 252 */         return null;
/*     */       }
/* 254 */       return getValue(integer.intValue());
/*     */     }
/*     */ 
/*     */ 
/*     */     
/*     */     public V put(K param1K, V param1V) {
/* 260 */       Integer integer = this.d.get(param1K);
/* 261 */       if (integer == null) {
/*     */         
/* 263 */         String str1 = dj(), str2 = String.valueOf(param1K), str3 = String.valueOf(this.d.j()); throw new IllegalArgumentException((new StringBuilder(9 + String.valueOf(str1).length() + String.valueOf(str2).length() + String.valueOf(str3).length())).append(str1).append(" ").append(str2).append(" not in ").append(str3).toString());
/*     */       } 
/* 265 */       return setValue(integer.intValue(), param1V);
/*     */     }
/*     */ 
/*     */     
/*     */     public V remove(Object param1Object) {
/* 270 */       throw new UnsupportedOperationException();
/*     */     }
/*     */     abstract String dj();
/*     */     abstract V getValue(int param1Int);
/*     */     public void clear() {
/* 275 */       throw new UnsupportedOperationException();
/*     */     }
/*     */ 
/*     */     
/*     */     abstract V setValue(int param1Int, V param1V);
/*     */   }
/*     */ 
/*     */   
/*     */   public bh<R> a() {
/* 284 */     return (bh<R>)this.a;
/*     */   }
/*     */ 
/*     */ 
/*     */ 
/*     */ 
/*     */   
/*     */   public bh<C> b() {
/* 292 */     return (bh)this.b;
/*     */   }
/*     */ 
/*     */ 
/*     */ 
/*     */ 
/*     */ 
/*     */ 
/*     */ 
/*     */ 
/*     */ 
/*     */ 
/*     */ 
/*     */ 
/*     */ 
/*     */   
/*     */   public V a(int paramInt1, int paramInt2) {
/* 309 */     D.b(paramInt1, this.a.size());
/* 310 */     D.b(paramInt2, this.b.size());
/* 311 */     return (V)this.a[paramInt1][paramInt2];
/*     */   }
/*     */ 
/*     */ 
/*     */ 
/*     */ 
/*     */ 
/*     */ 
/*     */ 
/*     */ 
/*     */ 
/*     */ 
/*     */ 
/*     */ 
/*     */ 
/*     */ 
/*     */   
/*     */   @com.google.b.a.a
/*     */   public V a(int paramInt1, int paramInt2, V paramV) {
/* 330 */     D.b(paramInt1, this.a.size());
/* 331 */     D.b(paramInt2, this.b.size());
/* 332 */     e e1 = this.a[paramInt1][paramInt2];
/* 333 */     this.a[paramInt1][paramInt2] = (e)paramV;
/* 334 */     return (V)e1;
/*     */   }
/*     */ 
/*     */ 
/*     */ 
/*     */ 
/*     */ 
/*     */ 
/*     */ 
/*     */ 
/*     */ 
/*     */ 
/*     */   
/*     */   @com.google.a.a.c
/*     */   public V[][] a(Class<V> paramClass) {
/* 349 */     Object[][] arrayOfObject = (Object[][])Array.newInstance(paramClass, new int[] { this.a.size(), this.b.size() });
/* 350 */     for (byte b = 0; b < this.a.size(); b++) {
/* 351 */       System.arraycopy(this.a[b], 0, arrayOfObject[b], 0, (this.a[b]).length);
/*     */     }
/* 353 */     return (V[][])arrayOfObject;
/*     */   }
/*     */ 
/*     */ 
/*     */ 
/*     */ 
/*     */ 
/*     */ 
/*     */ 
/*     */   
/*     */   @Deprecated
/*     */   public void clear() {
/* 365 */     throw new UnsupportedOperationException();
/*     */   }
/*     */ 
/*     */ 
/*     */ 
/*     */ 
/*     */   
/*     */   public void eV() {
/*     */     // Byte code:
/*     */     //   0: aload_0
/*     */     //   1: getfield a : [[Ljava/lang/Object;
/*     */     //   4: astore_1
/*     */     //   5: aload_1
/*     */     //   6: arraylength
/*     */     //   7: istore_2
/*     */     //   8: iconst_0
/*     */     //   9: istore_3
/*     */     //   10: iload_3
/*     */     //   11: iload_2
/*     */     //   12: if_icmpge -> 32
/*     */     //   15: aload_1
/*     */     //   16: iload_3
/*     */     //   17: aaload
/*     */     //   18: astore #4
/*     */     //   20: aload #4
/*     */     //   22: aconst_null
/*     */     //   23: invokestatic fill : ([Ljava/lang/Object;Ljava/lang/Object;)V
/*     */     //   26: iinc #3, 1
/*     */     //   29: goto -> 10
/*     */     //   32: return
/*     */     // Line number table:
/*     */     //   Java source line number -> byte code offset
/*     */     //   #370	-> 0
/*     */     //   #371	-> 20
/*     */     //   #370	-> 26
/*     */     //   #373	-> 32
/*     */   }
/*     */ 
/*     */ 
/*     */ 
/*     */ 
/*     */   
/*     */   public boolean contains(Object paramObject1, Object paramObject2) {
/* 381 */     return (d(paramObject1) && e(paramObject2));
/*     */   }
/*     */ 
/*     */ 
/*     */ 
/*     */ 
/*     */ 
/*     */   
/*     */   public boolean e(Object paramObject) {
/* 390 */     return this.c.containsKey(paramObject);
/*     */   }
/*     */ 
/*     */ 
/*     */ 
/*     */ 
/*     */ 
/*     */   
/*     */   public boolean d(Object paramObject) {
/* 399 */     return this.b.containsKey(paramObject);
/*     */   }
/*     */ 
/*     */ 
/*     */ 
/*     */ 
/*     */ 
/*     */   
/*     */   public boolean containsValue(Object paramObject) {
/*     */     // Byte code:
/*     */     //   0: aload_0
/*     */     //   1: getfield a : [[Ljava/lang/Object;
/*     */     //   4: astore_2
/*     */     //   5: aload_2
/*     */     //   6: arraylength
/*     */     //   7: istore_3
/*     */     //   8: iconst_0
/*     */     //   9: istore #4
/*     */     //   11: iload #4
/*     */     //   13: iload_3
/*     */     //   14: if_icmpge -> 72
/*     */     //   17: aload_2
/*     */     //   18: iload #4
/*     */     //   20: aaload
/*     */     //   21: astore #5
/*     */     //   23: aload #5
/*     */     //   25: astore #6
/*     */     //   27: aload #6
/*     */     //   29: arraylength
/*     */     //   30: istore #7
/*     */     //   32: iconst_0
/*     */     //   33: istore #8
/*     */     //   35: iload #8
/*     */     //   37: iload #7
/*     */     //   39: if_icmpge -> 66
/*     */     //   42: aload #6
/*     */     //   44: iload #8
/*     */     //   46: aaload
/*     */     //   47: astore #9
/*     */     //   49: aload_1
/*     */     //   50: aload #9
/*     */     //   52: invokestatic equal : (Ljava/lang/Object;Ljava/lang/Object;)Z
/*     */     //   55: ifeq -> 60
/*     */     //   58: iconst_1
/*     */     //   59: ireturn
/*     */     //   60: iinc #8, 1
/*     */     //   63: goto -> 35
/*     */     //   66: iinc #4, 1
/*     */     //   69: goto -> 11
/*     */     //   72: iconst_0
/*     */     //   73: ireturn
/*     */     // Line number table:
/*     */     //   Java source line number -> byte code offset
/*     */     //   #404	-> 0
/*     */     //   #405	-> 23
/*     */     //   #406	-> 49
/*     */     //   #407	-> 58
/*     */     //   #405	-> 60
/*     */     //   #404	-> 66
/*     */     //   #411	-> 72
/*     */   }
/*     */ 
/*     */ 
/*     */ 
/*     */ 
/*     */   
/*     */   public V get(Object paramObject1, Object paramObject2) {
/* 416 */     Integer integer1 = this.b.get(paramObject1);
/* 417 */     Integer integer2 = this.c.get(paramObject2);
/* 418 */     return (integer1 == null || integer2 == null) ? null : a(integer1.intValue(), integer2.intValue());
/*     */   }
/*     */ 
/*     */ 
/*     */ 
/*     */ 
/*     */   
/*     */   public boolean isEmpty() {
/* 426 */     return (this.a.isEmpty() || this.b.isEmpty());
/*     */   }
/*     */ 
/*     */ 
/*     */ 
/*     */ 
/*     */ 
/*     */ 
/*     */ 
/*     */   
/*     */   @com.google.b.a.a
/*     */   public V put(R paramR, C paramC, V paramV) {
/* 438 */     D.checkNotNull(paramR);
/* 439 */     D.checkNotNull(paramC);
/* 440 */     Integer integer1 = this.b.get(paramR);
/* 441 */     D.a((integer1 != null), "Row %s not in %s", paramR, this.a);
/* 442 */     Integer integer2 = this.c.get(paramC);
/* 443 */     D.a((integer2 != null), "Column %s not in %s", paramC, this.b);
/* 444 */     return a(integer1.intValue(), integer2.intValue(), paramV);
/*     */   }
/*     */ 
/*     */ 
/*     */ 
/*     */ 
/*     */ 
/*     */ 
/*     */ 
/*     */ 
/*     */ 
/*     */ 
/*     */ 
/*     */ 
/*     */ 
/*     */ 
/*     */ 
/*     */ 
/*     */   
/*     */   public void a(cY<? extends R, ? extends C, ? extends V> paramcY) {
/* 464 */     super.a(paramcY);
/*     */   }
/*     */ 
/*     */ 
/*     */ 
/*     */ 
/*     */ 
/*     */ 
/*     */ 
/*     */   
/*     */   @Deprecated
/*     */   @com.google.b.a.a
/*     */   public V e(Object paramObject1, Object paramObject2) {
/* 477 */     throw new UnsupportedOperationException();
/*     */   }
/*     */ 
/*     */ 
/*     */ 
/*     */ 
/*     */ 
/*     */ 
/*     */ 
/*     */ 
/*     */ 
/*     */ 
/*     */ 
/*     */ 
/*     */ 
/*     */   
/*     */   @com.google.b.a.a
/*     */   public V f(Object paramObject1, Object paramObject2) {
/* 495 */     Integer integer1 = this.b.get(paramObject1);
/* 496 */     Integer integer2 = this.c.get(paramObject2);
/* 497 */     if (integer1 == null || integer2 == null) {
/* 498 */       return null;
/*     */     }
/* 500 */     return a(integer1.intValue(), integer2.intValue(), null);
/*     */   }
/*     */ 
/*     */ 
/*     */ 
/*     */   
/*     */   public int size() {
/* 507 */     return this.a.size() * this.b.size();
/*     */   }
/*     */ 
/*     */ 
/*     */ 
/*     */ 
/*     */ 
/*     */ 
/*     */ 
/*     */ 
/*     */ 
/*     */ 
/*     */ 
/*     */ 
/*     */   
/*     */   public Set<cY.a<R, C, V>> j() {
/* 523 */     return super.j();
/*     */   }
/*     */ 
/*     */   
/*     */   Iterator<cY.a<R, C, V>> cellIterator() {
/* 528 */     return new b<cY.a<R, C, V>>(this, size())
/*     */       {
/*     */         protected cY.a<R, C, V> b(int param1Int) {
/* 531 */           return u.a(this.a, param1Int);
/*     */         }
/*     */       };
/*     */   }
/*     */ 
/*     */   
/*     */   Spliterator<cY.a<R, C, V>> c() {
/* 538 */     return D.a(
/* 539 */         size(), 273, this::a);
/*     */   }
/*     */   
/*     */   private cY.a<R, C, V> a(final int index) {
/* 543 */     return new cZ.a<R, C, V>(this) {
/* 544 */         final int dV = index / u.a(this.a).size();
/* 545 */         final int dW = index % u.a(this.a).size();
/*     */ 
/*     */         
/*     */         public R h() {
/* 549 */           return u.b(this.a).get(this.dV);
/*     */         }
/*     */ 
/*     */         
/*     */         public C i() {
/* 554 */           return u.a(this.a).get(this.dW);
/*     */         }
/*     */ 
/*     */         
/*     */         public V getValue() {
/* 559 */           return (V)this.a.a(this.dV, this.dW);
/*     */         }
/*     */       };
/*     */   }
/*     */   
/*     */   private V getValue(int paramInt) {
/* 565 */     int i = paramInt / this.b.size();
/* 566 */     int j = paramInt % this.b.size();
/* 567 */     return a(i, j);
/*     */   }
/*     */ 
/*     */ 
/*     */ 
/*     */ 
/*     */ 
/*     */ 
/*     */ 
/*     */ 
/*     */ 
/*     */ 
/*     */ 
/*     */ 
/*     */   
/*     */   public Map<R, V> a(C paramC) {
/* 583 */     D.checkNotNull(paramC);
/* 584 */     Integer integer = this.c.get(paramC);
/* 585 */     return (integer == null) ? bj.<R, V>f() : new b(this, integer.intValue());
/*     */   }
/*     */   
/*     */   private class b extends a<R, V> {
/*     */     final int dW;
/*     */     
/*     */     b(u this$0, int param1Int) {
/* 592 */       super(u.a(this$0));
/* 593 */       this.dW = param1Int;
/*     */     }
/*     */ 
/*     */     
/*     */     String dj() {
/* 598 */       return "Row";
/*     */     }
/*     */ 
/*     */     
/*     */     V getValue(int param1Int) {
/* 603 */       return (V)this.a.a(param1Int, this.dW);
/*     */     }
/*     */ 
/*     */     
/*     */     V setValue(int param1Int, V param1V) {
/* 608 */       return (V)this.a.a(param1Int, this.dW, param1V);
/*     */     }
/*     */   }
/*     */ 
/*     */ 
/*     */ 
/*     */ 
/*     */ 
/*     */ 
/*     */ 
/*     */   
/*     */   public bt<C> a() {
/* 620 */     return this.c.j();
/*     */   }
/*     */ 
/*     */ 
/*     */ 
/*     */   
/*     */   public Map<C, Map<R, V>> x() {
/* 627 */     e e1 = this.a;
/* 628 */     return (e1 == null) ? (this.a = (e)new c()) : e1;
/*     */   }
/*     */   
/*     */   private class c
/*     */     extends a<C, Map<R, V>> {
/*     */     private c(u this$0) {
/* 634 */       super(u.b(u.this));
/*     */     }
/*     */ 
/*     */     
/*     */     String dj() {
/* 639 */       return "Column";
/*     */     }
/*     */ 
/*     */     
/*     */     Map<R, V> a(int param1Int) {
/* 644 */       return new u.b(this.a, param1Int);
/*     */     }
/*     */ 
/*     */     
/*     */     Map<R, V> a(int param1Int, Map<R, V> param1Map) {
/* 649 */       throw new UnsupportedOperationException();
/*     */     }
/*     */ 
/*     */     
/*     */     public Map<R, V> a(C param1C, Map<R, V> param1Map) {
/* 654 */       throw new UnsupportedOperationException();
/*     */     }
/*     */   }
/*     */ 
/*     */ 
/*     */ 
/*     */ 
/*     */ 
/*     */ 
/*     */ 
/*     */ 
/*     */ 
/*     */ 
/*     */ 
/*     */ 
/*     */   
/*     */   public Map<C, V> b(R paramR) {
/* 671 */     D.checkNotNull(paramR);
/* 672 */     Integer integer = this.b.get(paramR);
/* 673 */     return (integer == null) ? bj.<C, V>f() : new d(this, integer.intValue());
/*     */   }
/*     */   
/*     */   private class d extends a<C, V> {
/*     */     final int dV;
/*     */     
/*     */     d(u this$0, int param1Int) {
/* 680 */       super(u.b(this$0));
/* 681 */       this.dV = param1Int;
/*     */     }
/*     */ 
/*     */     
/*     */     String dj() {
/* 686 */       return "Column";
/*     */     }
/*     */ 
/*     */     
/*     */     V getValue(int param1Int) {
/* 691 */       return (V)this.a.a(this.dV, param1Int);
/*     */     }
/*     */ 
/*     */     
/*     */     V setValue(int param1Int, V param1V) {
/* 696 */       return (V)this.a.a(this.dV, param1Int, param1V);
/*     */     }
/*     */   }
/*     */ 
/*     */ 
/*     */ 
/*     */ 
/*     */ 
/*     */ 
/*     */ 
/*     */   
/*     */   public bt<R> b() {
/* 708 */     return this.b.j();
/*     */   }
/*     */ 
/*     */ 
/*     */ 
/*     */   
/*     */   public Map<R, Map<C, V>> y() {
/* 715 */     e e1 = this.a;
/* 716 */     return (e1 == null) ? (this.a = new e()) : e1;
/*     */   }
/*     */   
/*     */   private class e
/*     */     extends a<R, Map<C, V>> {
/*     */     private e(u this$0) {
/* 722 */       super(u.a(u.this));
/*     */     }
/*     */ 
/*     */     
/*     */     String dj() {
/* 727 */       return "Row";
/*     */     }
/*     */ 
/*     */     
/*     */     Map<C, V> a(int param1Int) {
/* 732 */       return new u.d(this.a, param1Int);
/*     */     }
/*     */ 
/*     */     
/*     */     Map<C, V> a(int param1Int, Map<C, V> param1Map) {
/* 737 */       throw new UnsupportedOperationException();
/*     */     }
/*     */ 
/*     */     
/*     */     public Map<C, V> a(R param1R, Map<C, V> param1Map) {
/* 742 */       throw new UnsupportedOperationException();
/*     */     }
/*     */   }
/*     */ 
/*     */ 
/*     */ 
/*     */ 
/*     */ 
/*     */ 
/*     */ 
/*     */ 
/*     */ 
/*     */ 
/*     */   
/*     */   public Collection<V> values() {
/* 757 */     return super.values();
/*     */   }
/*     */ 
/*     */   
/*     */   Iterator<V> g() {
/* 762 */     return new b<V>(this, size())
/*     */       {
/*     */         protected V get(int param1Int) {
/* 765 */           return (V)u.a(this.a, param1Int);
/*     */         }
/*     */       };
/*     */   }
/*     */ 
/*     */   
/*     */   Spliterator<V> d() {
/* 772 */     return D.a(size(), 16, this::getValue);
/*     */   }
/*     */ }


/* Location:              C:\Arremate\Arremate.jar!\com\google\a\\\u.class
 * Java compiler version: 8 (52.0)
 * JD-Core Version:       1.1.3
 */